MANIFEST.in
setup.py
django_proxy_storage.egg-info/PKG-INFO
django_proxy_storage.egg-info/SOURCES.txt
django_proxy_storage.egg-info/dependency_links.txt
django_proxy_storage.egg-info/top_level.txt
proxy_storage/__init__.py
proxy_storage/compat.py
proxy_storage/models.py
proxy_storage/settings.py
proxy_storage/testutils.py
proxy_storage/utils.py
proxy_storage/db/__init__.py
proxy_storage/db/fields.py
proxy_storage/meta_backends/__init__.py
proxy_storage/meta_backends/base.py
proxy_storage/meta_backends/mongo.py
proxy_storage/meta_backends/orm.py
proxy_storage/storages/__init__.py
proxy_storage/storages/base.py
proxy_storage/storages/fallback.py